setup.cfg
setup.py
depynd/__init__.py
depynd.egg-info/PKG-INFO
depynd.egg-info/SOURCES.txt
depynd.egg-info/dependency_links.txt
depynd.egg-info/requires.txt
depynd.egg-info/top_level.txt
depynd/feature_selection/__init__.py
depynd/feature_selection/_mifs.py
depynd/feature_selection/_mrmr.py
depynd/feature_selection/_select.py
depynd/information/__init__.py
depynd/information/_dr.py
depynd/information/_information.py
depynd/information/_knn.py
depynd/information/_plugin.py
depynd/markov_networks/__init__.py
depynd/markov_networks/_glasso.py
depynd/markov_networks/_gsmn.py
depynd/markov_networks/_gsmple.py
depynd/markov_networks/_iamb.py
depynd/markov_networks/_jose.py
depynd/markov_networks/_select.py
depynd/markov_networks/_skeptic.py
depynd/markov_networks/_stars.py