Metadata-Version: 1.0
Name: depynd
Version: 0.6.2
Summary: Evaluating dependencies among random variables.
Home-page: https://github.com/y-takashina/depynd
Author: Yuya Takashina
Author-email: takashina2051@gmail.com
License: UNKNOWN
Platform: UNKNOWN
